ckanext_tables-1.7.0-py3.11-nspkg.pth
ckanext/tables/__init__.py
ckanext/tables/data_sources.py
ckanext/tables/exporters.py
ckanext/tables/formatters.py
ckanext/tables/generics.py
ckanext/tables/helpers.py
ckanext/tables/plugin.py
ckanext/tables/shared.py
ckanext/tables/table.py
ckanext/tables/types.py
ckanext/tables/utils.py
ckanext/tables/assets/webassets.yml
ckanext/tables/assets/css/style.css
ckanext/tables/assets/css/vendor/tabulator-theme.min.css
ckanext/tables/assets/css/vendor/tabulator.min.css
ckanext/tables/assets/js/tables-confirm.js
ckanext/tables/assets/js/tables-tabulator.js
ckanext/tables/assets/js/tables-toast.js
ckanext/tables/assets/js/vendor/tabulator.min.js
ckanext/tables/templates/tables/base.html
ckanext/tables/templates/tables/demo.html
ckanext/tables/templates/tables/render_table.html
ckanext/tables/templates/tables/formatters/actions.html
ckanext/tables/templates/tables/formatters/dialog_modal.html
ckanext/tables/templates/tables/formatters/json.html
ckanext/tables/templates/tables/macros/filter_item.html
ckanext/tables/templates/tables/snippets/loading_indicator.html
ckanext/tables/templates/tables/snippets/table_filters_modal.html
ckanext/tables/templates/tables/snippets/table_skeleton.html
ckanext/tables/tests/__init__.py
ckanext/tables_demo/__init__.py
ckanext/tables_demo/plugin.py
ckanext/tables_demo/table.py
ckanext/tables_demo/utils.py
ckanext/tables_demo/views.py
ckanext_tables-1.7.0.dist-info/licenses/LICENSE
ckanext_tables-1.7.0.dist-info/METADATA
ckanext_tables-1.7.0.dist-info/WHEEL
ckanext_tables-1.7.0.dist-info/entry_points.txt
ckanext_tables-1.7.0.dist-info/namespace_packages.txt
ckanext_tables-1.7.0.dist-info/top_level.txt
ckanext_tables-1.7.0.dist-info/RECORD
