Metadata-Version: 2.4
Name: ckanext-tables
Version: 1.7.0
Summary: An extension to render dynamic tables
Author-email: Oleksandr Cherniavskiy <mutantsan@gmail.com>
License: AGPL
Project-URL: Homepage, https://github.com/DataShades/ckanext-tables
Keywords: CKAN
Classifier: Development Status :: 4 - Beta
Classifier: License :: OSI Approved :: GNU Affero General Public License v3 or later (AGPLv3+)
Classifier: Programming Language :: Python :: 3.10
Classifier: Programming Language :: Python :: 3.11
Classifier: Programming Language :: Python :: 3.12
License-File: LICENSE
Provides-Extra: xlsx
Requires-Dist: openpyxl<4.0.0,>=3.1.2; extra == "xlsx"
Provides-Extra: test
Requires-Dist: pytest-ckan; extra == "test"
Provides-Extra: docs
Requires-Dist: mkdocs; extra == "docs"
Requires-Dist: mkdocs-material; extra == "docs"
Requires-Dist: mkdocstrings; extra == "docs"
Requires-Dist: mkdocstrings-python; extra == "docs"
Dynamic: license-file
